lueur/__init__.py
lueur/attributions.py
lueur/concepts/__init__.py
lueur/concepts/craft.py
lueur/inference.py
lueur/neuro_datasets.py
lueur/regressors.py
lueur/timm_models.py
lueur/utils.py
lueur_torch-0.0.1.dist-info/LICENSE
lueur_torch-0.0.1.dist-info/METADATA
lueur_torch-0.0.1.dist-info/WHEEL
lueur_torch-0.0.1.dist-info/RECORD
