Metadata-Version: 2.3
Name: lueur-torch
Version: 0.0.1
Summary: Lueur is a lightweight framework for Neuro Interpretability.
License: MIT
Author: Thomas Fel
Author-email: tfel@g.harvard.edu
Requires-Python: >=3.11
Classifier: License :: OSI Approved :: MIT License
Classifier: Programming Language :: Python :: 3
Classifier: Programming Language :: Python :: 3.11
Classifier: Programming Language :: Python :: 3.12
Classifier: Programming Language :: Python :: 3.13
Requires-Dist: brainscore_vision
Requires-Dist: einops
Requires-Dist: matplotlib
Requires-Dist: numpy
Requires-Dist: opencv-python
Requires-Dist: overcomplete
Requires-Dist: scikit-image
Requires-Dist: scikit-learn (>=1.2.0,<2.0.0)
Requires-Dist: timm
Requires-Dist: torch
Requires-Dist: torchvision
